skgstat_uncertainty/__init__.py
skgstat_uncertainty/api.py
skgstat_uncertainty/db.py
skgstat_uncertainty/models.py
skgstat_uncertainty/chapters/__init__.py
skgstat_uncertainty/chapters/data_manage.py
skgstat_uncertainty/chapters/kriging.py
skgstat_uncertainty/chapters/learn_geostatistics.py
skgstat_uncertainty/chapters/main.py
skgstat_uncertainty/chapters/model_compare.py
skgstat_uncertainty/chapters/model_fitting.py
skgstat_uncertainty/chapters/model_simulation.py
skgstat_uncertainty/chapters/variogram.py
skgstat_uncertainty/components/__init__.py
skgstat_uncertainty/components/data_edit.py
skgstat_uncertainty/components/data_selects.py
skgstat_uncertainty/components/filters.py
skgstat_uncertainty/components/plotting.py
skgstat_uncertainty/components/tables.py
skgstat_uncertainty/components/utils.py
skgstat_uncertainty/processor/__init__.py
skgstat_uncertainty/processor/dic.py
skgstat_uncertainty/processor/fit.py
skgstat_uncertainty/processor/propagation.py
skgstat_uncertainty/processor/rm.py
skgstat_uncertainty/processor/sampling.py
skgstat_uncertainty/processor/utils.py
skgstat_uncertainty/utils/__init__.py
skgstat_uncertainty/utils/vario_tools.py
skgstat_uncertainty-1.8.0.dist-info/METADATA
skgstat_uncertainty-1.8.0.dist-info/WHEEL
skgstat_uncertainty-1.8.0.dist-info/top_level.txt
skgstat_uncertainty-1.8.0.dist-info/RECORD
