Metadata-Version: 2.1
Name: skgstat-uncertainty
Version: 1.8.0
Summary: Uncertainty analysis tool for SciKit-GStat
License: MIT License
Requires-Dist: streamlit (>=1.0.0)
Requires-Dist: pandas
Requires-Dist: scipy (==1.8.0)
Requires-Dist: scikit-gstat (>=1.0.0)
Requires-Dist: scikit-info (>=0.4.0)
Requires-Dist: gstools (>=1.3.0)
Requires-Dist: sqlalchemy
Requires-Dist: fire
Requires-Dist: plotly
Requires-Dist: kaleido
Requires-Dist: streamlit-card-select (>=0.3.0)
